{
    "algorithm": "Quick Sort 32",
    "results": [
        {
            "items": 2500000,
            "time": 426627
        },
        {
            "items": 5000000,
            "time": 1002218
        },
        {
            "items": 7500000,
            "time": 1281305
        },
        {
            "items": 10000000,
            "time": 1705292
        },
        {
            "items": 12500000,
            "time": 2122201
        },
        {
            "items": 15000000,
            "time": 2377000
        },
        {
            "items": 17500000,
            "time": 2640416
        },
        {
            "items": 20000000,
            "time": 3221577
        },
        {
            "items": 22500000,
            "time": 3648475
        },
        {
            "items": 25000000,
            "time": 4482453
        },
        {
            "items": 27500000,
            "time": 4745065
        },
        {
            "items": 30000000,
            "time": 4871660
        },
        {
            "items": 32500000,
            "time": 5393650
        },
        {
            "items": 35000000,
            "time": 5148553
        },
        {
            "items": 37500000,
            "time": 6462254
        },
        {
            "items": 40000000,
            "time": 6916756
        },
        {
            "items": 42500000,
            "time": 6881154
        },
        {
            "items": 45000000,
            "time": 7580720
        },
        {
            "items": 47500000,
            "time": 7799471
        },
        {
            "items": 50000000,
            "time": 9032354
        },
        {
            "items": 52500000,
            "time": 7831984
        },
        {
            "items": 55000000,
            "time": 9950372
        },
        {
            "items": 57500000,
            "time": 10330184
        },
        {
            "items": 60000000,
            "time": 10371286
        },
        {
            "items": 62500000,
            "time": 10697772
        },
        {
            "items": 65000000,
            "time": 12329954
        },
        {
            "items": 67500000,
            "time": 10866422
        },
        {
            "items": 70000000,
            "time": 13053908
        },
        {
            "items": 72500000,
            "time": 12946326
        },
        {
            "items": 75000000,
            "time": 13118687
        },
        {
            "items": 77500000,
            "time": 13932534
        },
        {
            "items": 80000000,
            "time": 16057544
        },
        {
            "items": 82500000,
            "time": 16641436
        },
        {
            "items": 85000000,
            "time": 16932753
        },
        {
            "items": 87500000,
            "time": 15043016
        },
        {
            "items": 90000000,
            "time": 16335511
        },
        {
            "items": 92500000,
            "time": 17003365
        },
        {
            "items": 95000000,
            "time": 19738359
        },
        {
            "items": 97500000,
            "time": 19911757
        },
        {
            "items": 100000000,
            "time": 17672819
        },
        {
            "items": 102500000,
            "time": 18587325
        },
        {
            "items": 105000000,
            "time": 20846886
        },
        {
            "items": 107500000,
            "time": 19718010
        },
        {
            "items": 110000000,
            "time": 21974229
        },
        {
            "items": 112500000,
            "time": 18640909
        },
        {
            "items": 115000000,
            "time": 22719422
        },
        {
            "items": 117500000,
            "time": 21115660
        },
        {
            "items": 120000000,
            "time": 23272573
        },
        {
            "items": 122500000,
            "time": 22543483
        },
        {
            "items": 125000000,
            "time": 21251761
        },
        {
            "items": 127500000,
            "time": 22731696
        },
        {
            "items": 130000000,
            "time": 25352026
        },
        {
            "items": 132500000,
            "time": 25820890
        },
        {
            "items": 135000000,
            "time": 26068782
        },
        {
            "items": 137500000,
            "time": 24672759
        },
        {
            "items": 140000000,
            "time": 27441691
        },
        {
            "items": 142500000,
            "time": 23593844
        },
        {
            "items": 145000000,
            "time": 28341931
        },
        {
            "items": 147500000,
            "time": 28893209
        },
        {
            "items": 150000000,
            "time": 27351053
        },
        {
            "items": 152500000,
            "time": 27779366
        },
        {
            "items": 155000000,
            "time": 27892714
        },
        {
            "items": 157500000,
            "time": 28502413
        },
        {
            "items": 160000000,
            "time": 31669863
        },
        {
            "items": 162500000,
            "time": 29581792
        },
        {
            "items": 165000000,
            "time": 32544375
        },
        {
            "items": 167500000,
            "time": 33138821
        },
        {
            "items": 170000000,
            "time": 33831139
        },
        {
            "items": 172500000,
            "time": 30193745
        },
        {
            "items": 175000000,
            "time": 34790020
        },
        {
            "items": 177500000,
            "time": 35518252
        },
        {
            "items": 180000000,
            "time": 32904367
        },
        {
            "items": 182500000,
            "time": 33443710
        },
        {
            "items": 185000000,
            "time": 37922692
        },
        {
            "items": 187500000,
            "time": 38152387
        },
        {
            "items": 190000000,
            "time": 33563196
        },
        {
            "items": 192500000,
            "time": 35080398
        },
        {
            "items": 195000000,
            "time": 39037399
        },
        {
            "items": 197500000,
            "time": 36272110
        },
        {
            "items": 200000000,
            "time": 40392065
        },
        {
            "items": 202500000,
            "time": 35971872
        },
        {
            "items": 205000000,
            "time": 37355594
        },
        {
            "items": 207500000,
            "time": 41828045
        },
        {
            "items": 210000000,
            "time": 38768280
        },
        {
            "items": 212500000,
            "time": 42491541
        },
        {
            "items": 215000000,
            "time": 37323560
        },
        {
            "items": 217500000,
            "time": 39350614
        },
        {
            "items": 220000000,
            "time": 44172164
        },
        {
            "items": 222500000,
            "time": 44995619
        },
        {
            "items": 225000000,
            "time": 44934629
        },
        {
            "items": 227500000,
            "time": 42199243
        },
        {
            "items": 230000000,
            "time": 46721329
        },
        {
            "items": 232500000,
            "time": 47205432
        },
        {
            "items": 235000000,
            "time": 42791780
        },
        {
            "items": 237500000,
            "time": 43622474
        },
        {
            "items": 240000000,
            "time": 44721994
        },
        {
            "items": 242500000,
            "time": 48315588
        },
        {
            "items": 245000000,
            "time": 36426469
        },
        {
            "items": 247500000,
            "time": 36510366
        },
        {
            "items": 250000000,
            "time": 37182870
        }
    ],
    "timeUnit": "us"
}
